{
  "doc_id": "dr_kruc",
  "source_url": "https://www.kdic.or.kr/di/relsite/PbcrKrncLblarb/selectScrn.do",
  "business_function": "채무조정 안내",
  "sub_category": "KR&C 채무조정",
  "page_title": "채무조정",
  "required": true,
  "note": "예솜24 5.1-5.3-5.4와 동일 개념을 KR&C 페이지가 더 상세히 제공",
  "summary": "케이알앤씨(KR&C)가 파산재단·부실금융회사에서 인수한 대출채권 채무자 대상 채무조정 안내. 신청자격(변제를 기대할 수 없는 주채무자·보증채무자), 신청 불가 사유 4가지, 본인·대리인 구비서류(채무조정신청서, 해제조건부 채무면제 각서 등)를 담는다.",
  "collected_at": "2026-07-13",
  "links": [],
  "attachments": [],
  "form_attachments": [],
  "videos": [],
  "images": [
    {
      "alt": "지원내용",
      "url": "https://www.kdic.or.kr/assets/images/img-DI-IAC-000-01-pc.jpg"
    },
    {
      "alt": "채무조정 절차",
      "url": "https://www.kdic.or.kr/assets/images/img-DI-IAC-000-02-pc.jpg"
    }
  ]
}
